greenophy/__init__.py
greenophy/client.py
greenophy-0.1.5.dist-info/METADATA
greenophy-0.1.5.dist-info/WHEEL
greenophy-0.1.5.dist-info/top_level.txt
greenophy-0.1.5.dist-info/RECORD
