Metadata-Version: 2.4
Name: greenophy
Version: 0.1.5
Summary: Python client for the hosted Greenophy ESG substantiveness classification API.
Author-email: Greenophy <contact@greenophy.com>
License: MIT
Project-URL: Homepage, https://greenophy.com
Project-URL: Source, https://greenophy.com
Requires-Python: >=3.9
Requires-Dist: requests>=2.31
